[
  {
    "date": "2026-03-20",
    "curve": {
      "DGS1MO": 3.73,
      "DGS3MO": 3.73,
      "DGS6MO": 3.74,
      "DGS1": 3.68,
      "DGS2": 3.76,
      "DGS3": 3.76,
      "DGS5": 3.87,
      "DGS7": 4.05,
      "DGS10": 4.26,
      "DGS20": 4.84,
      "DGS30": 4.88
    }
  },
  {
    "date": "2026-03-23",
    "curve": {
      "DGS1MO": 3.73,
      "DGS3MO": 3.73,
      "DGS6MO": 3.76,
      "DGS1": 3.73,
      "DGS2": 3.79,
      "DGS3": 3.79,
      "DGS5": 3.88,
      "DGS7": 4.06,
      "DGS10": 4.25,
      "DGS20": 4.82,
      "DGS30": 4.83
    }
  },
  {
    "date": "2026-03-24",
    "curve": {
      "DGS1MO": 3.73,
      "DGS3MO": 3.74,
      "DGS6MO": 3.79,
      "DGS1": 3.8,
      "DGS2": 3.88,
      "DGS3": 3.9,
      "DGS5": 4.01,
      "DGS7": 4.2,
      "DGS10": 4.39,
      "DGS20": 4.97,
      "DGS30": 4.96
    }
  },
  {
    "date": "2026-03-25",
    "curve": {
      "DGS1MO": 3.73,
      "DGS3MO": 3.74,
      "DGS6MO": 3.77,
      "DGS1": 3.76,
      "DGS2": 3.83,
      "DGS3": 3.85,
      "DGS5": 3.95,
      "DGS7": 4.15,
      "DGS10": 4.34,
      "DGS20": 4.93,
      "DGS30": 4.91
    }
  },
  {
    "date": "2026-03-26",
    "curve": {
      "DGS1MO": 3.74,
      "DGS3MO": 3.74,
      "DGS6MO": 3.78,
      "DGS1": 3.81,
      "DGS2": 3.9,
      "DGS3": 3.93,
      "DGS5": 4.03,
      "DGS7": 4.21,
      "DGS10": 4.39,
      "DGS20": 4.95,
      "DGS30": 4.94
    }
  }
]